{
  "matchup": {
    "attacker": "Deejay",
    "defender": "Ryu",
    "patch": "2024-12",
    "source": "wiki.supercombo.gg + ultimateframedata.com"
  },
  "punishes": [
    {
      "id": "ryu_standing_light_punch",
      "moveName": "Standing Light Punch",
      "category": "normal",
      "onBlock": -1,
      "startup": "4",
      "active": "3",
      "recovery": null,
      "punishWindow": null,
      "bestPunish": null,
      "notes": null,
      "imageURL": "https://ultimateframedata.com/sf6/hitboxes/Ryu/ryu-st-lp.gif",
      "command": "5LP"
    },
    {
      "id": "ryu_standing_medium_punch",
      "moveName": "Standing Medium Punch",
      "category": "normal",
      "onBlock": -1,
      "startup": "6",
      "active": "4",
      "recovery": null,
      "punishWindow": null,
      "bestPunish": null,
      "notes": null,
      "imageURL": "https://ultimateframedata.com/sf6/hitboxes/Ryu/ryu-st-mp-mar2026.gif",
      "command": "5MP"
    },
    {
      "id": "ryu_standing_heavy_punch",
      "moveName": "Standing Heavy Punch",
      "category": "normal",
      "onBlock": -2,
      "startup": "10",
      "active": "5",
      "recovery": null,
      "punishWindow": null,
      "bestPunish": null,
      "notes": null,
      "imageURL": "https://ultimateframedata.com/sf6/hitboxes/Ryu/ryu-st-hp.gif",
      "command": "5HP"
    },
    {
      "id": "ryu_standing_light_kick",
      "moveName": "Standing Light Kick",
      "category": "normal",
      "onBlock": -4,
      "startup": "5",
      "active": "3",
      "recovery": null,
      "punishWindow": null,
      "bestPunish": null,
      "notes": null,
      "imageURL": "https://ultimateframedata.com/sf6/hitboxes/Ryu/ryu-st-lk.gif",
      "command": "5LK"
    },
    {
      "id": "ryu_standing_medium_kick",
      "moveName": "Standing Medium Kick",
      "category": "normal",
      "onBlock": -4,
      "startup": "9",
      "active": "3",
      "recovery": null,
      "punishWindow": null,
      "bestPunish": null,
      "notes": null,
      "imageURL": "https://ultimateframedata.com/sf6/hitboxes/Ryu/ryu-st-mk.gif",
      "command": "5MK"
    },
    {
      "id": "ryu_standing_heavy_kick",
      "moveName": "Standing Heavy Kick",
      "category": "normal",
      "onBlock": 1,
      "startup": "12",
      "active": "4",
      "recovery": null,
      "punishWindow": null,
      "bestPunish": null,
      "notes": null,
      "imageURL": "https://ultimateframedata.com/sf6/hitboxes/Ryu/ryu-st-hk.gif",
      "command": "5HK"
    },
    {
      "id": "ryu_crouching_light_punch",
      "moveName": "Crouching Light Punch",
      "category": "normal",
      "onBlock": -1,
      "startup": "4",
      "active": "2",
      "recovery": null,
      "punishWindow": null,
      "bestPunish": null,
      "notes": null,
      "imageURL": "https://ultimateframedata.com/sf6/hitboxes/Ryu/ryu-cr-lp-1.2.gif",
      "command": "2LP"
    },
    {
      "id": "ryu_crouching_medium_punch",
      "moveName": "Crouching Medium Punch",
      "category": "normal",
      "onBlock": 0,
      "startup": "6",
      "active": "4",
      "recovery": null,
      "punishWindow": null,
      "bestPunish": null,
      "notes": null,
      "imageURL": "https://ultimateframedata.com/sf6/hitboxes/Ryu/ryu-cr-mp-june2025.gif",
      "command": "2MP"
    },
    {
      "id": "ryu_crouching_heavy_punch",
      "moveName": "Crouching Heavy Punch",
      "category": "normal",
      "onBlock": -7,
      "startup": "9",
      "active": "6",
      "recovery": null,
      "punishWindow": null,
      "bestPunish": null,
      "notes": null,
      "imageURL": "https://ultimateframedata.com/sf6/hitboxes/Ryu/ryu-cr-hp-aa.gif",
      "command": "2HP"
    },
    {
      "id": "ryu_crouching_light_kick",
      "moveName": "Crouching Light Kick",
      "category": "normal",
      "onBlock": -3,
      "startup": "5",
      "active": "2",
      "recovery": null,
      "punishWindow": null,
      "bestPunish": null,
      "notes": null,
      "imageURL": "https://ultimateframedata.com/sf6/hitboxes/Ryu/ryu-cr-lk.gif",
      "command": "2LK"
    },
    {
      "id": "ryu_crouching_medium_kick",
      "moveName": "Crouching Medium Kick",
      "category": "normal",
      "onBlock": -6,
      "startup": "8",
      "active": "3",
      "recovery": null,
      "punishWindow": null,
      "bestPunish": null,
      "notes": null,
      "imageURL": "https://ultimateframedata.com/sf6/hitboxes/Ryu/ryu-cr-mk.gif",
      "command": "2MK"
    },
    {
      "id": "ryu_crouching_heavy_kick",
      "moveName": "Crouching Heavy Kick",
      "category": "normal",
      "onBlock": -12,
      "startup": "9",
      "active": "3",
      "recovery": null,
      "punishWindow": null,
      "bestPunish": null,
      "notes": null,
      "imageURL": "https://ultimateframedata.com/sf6/hitboxes/Ryu/ryu-cr-hk-june2025.gif",
      "command": "2HK"
    },
    {
      "id": "ryu_forward_medium_punch_collarbone_breaker",
      "moveName": "Forward + Medium Punch (Collarbone Breaker)",
      "category": "unique",
      "onBlock": -3,
      "startup": "20",
      "active": "4",
      "recovery": null,
      "punishWindow": null,
      "bestPunish": null,
      "notes": null,
      "imageURL": "https://ultimateframedata.com/sf6/hitboxes/Ryu/ryu-f+mp.gif"
    },
    {
      "id": "ryu_forward_heavy_punch_solar_plexus_strike",
      "moveName": "Forward + Heavy Punch (Solar Plexus Strike)",
      "category": "unique",
      "onBlock": 3,
      "startup": "20",
      "active": "5",
      "recovery": null,
      "punishWindow": null,
      "bestPunish": null,
      "notes": null,
      "imageURL": "https://ultimateframedata.com/sf6/hitboxes/Ryu/ryu-f+hp.gif"
    },
    {
      "id": "ryu_back_heavy_punch",
      "moveName": "Back + Heavy Punch",
      "category": "unique",
      "onBlock": -13,
      "startup": "7",
      "active": "4",
      "recovery": null,
      "punishWindow": null,
      "bestPunish": null,
      "notes": null,
      "imageURL": "https://ultimateframedata.com/sf6/hitboxes/Ryu/ryu-b+hp.gif"
    },
    {
      "id": "ryu_back_heavy_kick_axe_kick",
      "moveName": "Back + Heavy Kick (Axe Kick)",
      "category": "unique",
      "onBlock": -4,
      "startup": "10",
      "active": "5, 3",
      "recovery": null,
      "punishWindow": null,
      "bestPunish": null,
      "notes": null,
      "imageURL": "https://ultimateframedata.com/sf6/hitboxes/Ryu/ryu-b+hk.gif"
    },
    {
      "id": "ryu_forward_heavy_kick_whirlwind_kick",
      "moveName": "Forward + Heavy Kick (Whirlwind Kick)",
      "category": "unique",
      "onBlock": -4,
      "startup": "16",
      "active": "4",
      "recovery": null,
      "punishWindow": null,
      "bestPunish": null,
      "notes": null,
      "imageURL": "https://ultimateframedata.com/sf6/hitboxes/Ryu/ryu-f+hk-may2024.gif"
    },
    {
      "id": "ryu_hadoken_light_punch",
      "moveName": "Hadoken (Light Punch)",
      "category": "special",
      "onBlock": -5,
      "startup": "16",
      "active": "...",
      "recovery": null,
      "punishWindow": null,
      "bestPunish": null,
      "notes": null,
      "imageURL": "https://ultimateframedata.com/sf6/hitboxes/Ryu/RyuJab1.gif",
      "command": "236P"
    },
    {
      "id": "ryu_hadoken_medium_punch",
      "moveName": "Hadoken (Medium Punch)",
      "category": "special",
      "onBlock": -7,
      "startup": "14",
      "active": "...",
      "recovery": null,
      "punishWindow": null,
      "bestPunish": null,
      "notes": null,
      "imageURL": "https://ultimateframedata.com/sf6/hitboxes/Ryu/RyuJab1.gif",
      "command": "236P"
    },
    {
      "id": "ryu_hadoken_heavy_punch",
      "moveName": "Hadoken (Heavy Punch)",
      "category": "special",
      "onBlock": -9,
      "startup": "12",
      "active": "...",
      "recovery": null,
      "punishWindow": null,
      "bestPunish": null,
      "notes": null,
      "imageURL": "https://ultimateframedata.com/sf6/hitboxes/Ryu/RyuJab1.gif",
      "command": "236P"
    },
    {
      "id": "ryu_hadoken_overdrive",
      "moveName": "Hadoken (Overdrive)",
      "category": "special",
      "onBlock": -1,
      "startup": "12",
      "active": "...",
      "recovery": null,
      "punishWindow": null,
      "bestPunish": null,
      "notes": null,
      "imageURL": "https://ultimateframedata.com/sf6/hitboxes/Ryu/RyuJab1.gif",
      "command": "236P"
    },
    {
      "id": "ryu_shoryuken_light_punch",
      "moveName": "Shoryuken (Light Punch)",
      "category": "special",
      "onBlock": -23,
      "startup": "5",
      "active": "10",
      "recovery": null,
      "punishWindow": null,
      "bestPunish": null,
      "notes": null,
      "imageURL": "https://ultimateframedata.com/sf6/hitboxes/Ryu/ryu-shoryuken-lp.gif",
      "command": "623P"
    },
    {
      "id": "ryu_shoryuken_medium_punch",
      "moveName": "Shoryuken (Medium Punch)",
      "category": "special",
      "onBlock": -32,
      "startup": "6",
      "active": "10",
      "recovery": null,
      "punishWindow": null,
      "bestPunish": null,
      "notes": null,
      "imageURL": "https://ultimateframedata.com/sf6/hitboxes/Ryu/ryu-shoryuken-mp.gif",
      "command": "623P"
    },
    {
      "id": "ryu_shoryuken_heavy_punch",
      "moveName": "Shoryuken (Heavy Punch)",
      "category": "special",
      "onBlock": -36,
      "startup": "7",
      "active": "10",
      "recovery": null,
      "punishWindow": null,
      "bestPunish": null,
      "notes": null,
      "imageURL": "https://ultimateframedata.com/sf6/hitboxes/Ryu/ryu-shoryuken-hp.gif",
      "command": "623P"
    },
    {
      "id": "ryu_shoryuken_overdrive",
      "moveName": "Shoryuken (Overdrive)",
      "category": "special",
      "onBlock": -40,
      "startup": "6",
      "active": "10",
      "recovery": null,
      "punishWindow": null,
      "bestPunish": null,
      "notes": null,
      "imageURL": "https://ultimateframedata.com/sf6/hitboxes/Ryu/ryu-shoryuken-od.gif",
      "command": "623P"
    },
    {
      "id": "ryu_tatsumaki_senpu_kyaku_light_kick",
      "moveName": "Tatsumaki Senpu-kyaku (Light Kick)",
      "category": "special",
      "onBlock": -15,
      "startup": "12",
      "active": "3",
      "recovery": null,
      "punishWindow": null,
      "bestPunish": null,
      "notes": null,
      "imageURL": "https://ultimateframedata.com/sf6/hitboxes/Ryu/RyuJab1.gif",
      "command": "214K"
    },
    {
      "id": "ryu_tatsumaki_senpu_kyaku_medium_kick",
      "moveName": "Tatsumaki Senpu-kyaku (Medium Kick)",
      "category": "special",
      "onBlock": -13,
      "startup": "14...",
      "active": "2, 2",
      "recovery": null,
      "punishWindow": null,
      "bestPunish": null,
      "notes": null,
      "imageURL": "https://ultimateframedata.com/sf6/hitboxes/Ryu/RyuJab1.gif",
      "command": "214K"
    },
    {
      "id": "ryu_tatsumaki_senpu_kyaku_heavy_kick",
      "moveName": "Tatsumaki Senpu-kyaku (Heavy Kick)",
      "category": "special",
      "onBlock": -13,
      "startup": "16...",
      "active": "2, 2, 2",
      "recovery": null,
      "punishWindow": null,
      "bestPunish": null,
      "notes": null,
      "imageURL": "https://ultimateframedata.com/sf6/hitboxes/Ryu/RyuJab1.gif",
      "command": "214K"
    },
    {
      "id": "ryu_tatsumaki_senpu_kyaku_overdrive",
      "moveName": "Tatsumaki Senpu-kyaku (Overdrive)",
      "category": "special",
      "onBlock": -14,
      "startup": "13...",
      "active": "2, 2, 2, 2, 2",
      "recovery": null,
      "punishWindow": null,
      "bestPunish": null,
      "notes": null,
      "imageURL": "https://ultimateframedata.com/sf6/hitboxes/Ryu/RyuJab1.gif",
      "command": "214K"
    },
    {
      "id": "ryu_aerial_tatsumaki_senpu_kyaku",
      "moveName": "Aerial Tatsumaki Senpu-kyaku",
      "category": "special",
      "onBlock": -1,
      "startup": "11",
      "active": "2",
      "recovery": null,
      "punishWindow": null,
      "bestPunish": null,
      "notes": null,
      "imageURL": "https://ultimateframedata.com/sf6/hitboxes/Ryu/RyuJab1.gif",
      "command": "j.214K"
    },
    {
      "id": "ryu_forward_jump_only_aerial_tatsumaki_senpu_kyaku_overdrive",
      "moveName": "(Forward Jump Only) Aerial Tatsumaki Senpu-kyaku (Overdrive)",
      "category": "special",
      "onBlock": -30,
      "startup": "11",
      "active": "2, 3, 3, 3, 2",
      "recovery": null,
      "punishWindow": null,
      "bestPunish": null,
      "notes": null,
      "imageURL": "https://ultimateframedata.com/sf6/hitboxes/Ryu/RyuJab1.gif"
    },
    {
      "id": "ryu_high_blade_kick_light_kick",
      "moveName": "High Blade Kick (Light Kick)",
      "category": "special",
      "onBlock": -11,
      "startup": "14",
      "active": "6",
      "recovery": null,
      "punishWindow": null,
      "bestPunish": null,
      "notes": null,
      "imageURL": "https://ultimateframedata.com/sf6/hitboxes/Ryu/RyuJab1.gif",
      "command": "236K"
    },
    {
      "id": "ryu_high_blade_kick_medium_kick",
      "moveName": "High Blade Kick (Medium Kick)",
      "category": "special",
      "onBlock": -8,
      "startup": "18",
      "active": "9",
      "recovery": null,
      "punishWindow": null,
      "bestPunish": null,
      "notes": null,
      "imageURL": "https://ultimateframedata.com/sf6/hitboxes/Ryu/RyuJab1.gif",
      "command": "236K"
    },
    {
      "id": "ryu_high_blade_kick_heavy_kick",
      "moveName": "High Blade Kick (Heavy Kick)",
      "category": "special",
      "onBlock": -3,
      "startup": "27",
      "active": "9",
      "recovery": null,
      "punishWindow": null,
      "bestPunish": null,
      "notes": null,
      "imageURL": "https://ultimateframedata.com/sf6/hitboxes/Ryu/RyuJab1.gif",
      "command": "236K"
    },
    {
      "id": "ryu_high_blade_kick_overdrive",
      "moveName": "High Blade Kick (Overdrive)",
      "category": "special",
      "onBlock": -18,
      "startup": "17",
      "active": "5",
      "recovery": null,
      "punishWindow": null,
      "bestPunish": null,
      "notes": null,
      "imageURL": "https://ultimateframedata.com/sf6/hitboxes/Ryu/RyuJab1.gif",
      "command": "236K"
    },
    {
      "id": "ryu_hashogeki_light_punch",
      "moveName": "Hashogeki (Light Punch)",
      "category": "special",
      "onBlock": -3,
      "startup": "12",
      "active": "6",
      "recovery": null,
      "punishWindow": null,
      "bestPunish": null,
      "notes": null,
      "imageURL": "https://ultimateframedata.com/sf6/hitboxes/Ryu/RyuJab1.gif",
      "command": "214P"
    },
    {
      "id": "ryu_hashogeki_medium_punch",
      "moveName": "Hashogeki (Medium Punch)",
      "category": "special",
      "onBlock": -6,
      "startup": "19",
      "active": "6",
      "recovery": null,
      "punishWindow": null,
      "bestPunish": null,
      "notes": null,
      "imageURL": "https://ultimateframedata.com/sf6/hitboxes/Ryu/RyuJab1.gif",
      "command": "214P"
    },
    {
      "id": "ryu_hashogeki_heavy_punch",
      "moveName": "Hashogeki (Heavy Punch)",
      "category": "special",
      "onBlock": 2,
      "startup": "30",
      "active": "6",
      "recovery": null,
      "punishWindow": null,
      "bestPunish": null,
      "notes": null,
      "imageURL": "https://ultimateframedata.com/sf6/hitboxes/Ryu/RyuJab1.gif",
      "command": "214P"
    },
    {
      "id": "ryu_hashogeki_overdrive",
      "moveName": "Hashogeki (Overdrive)",
      "category": "special",
      "onBlock": 3,
      "startup": "18",
      "active": "6",
      "recovery": null,
      "punishWindow": null,
      "bestPunish": null,
      "notes": null,
      "imageURL": "https://ultimateframedata.com/sf6/hitboxes/Ryu/RyuJab1.gif",
      "command": "214P"
    },
    {
      "id": "ryu_denjin_charge",
      "moveName": "Denjin Charge",
      "category": "special",
      "onBlock": 0,
      "startup": "52",
      "active": null,
      "recovery": null,
      "punishWindow": null,
      "bestPunish": null,
      "notes": null,
      "imageURL": "https://ultimateframedata.com/sf6/hitboxes/Ryu/RyuJab1.gif",
      "command": "22P"
    },
    {
      "id": "ryu_hadoken_denjin_charge",
      "moveName": "Hadoken (Denjin Charge)",
      "category": "special",
      "onBlock": -1,
      "startup": "12",
      "active": "...",
      "recovery": null,
      "punishWindow": null,
      "bestPunish": null,
      "notes": null,
      "imageURL": "https://ultimateframedata.com/sf6/hitboxes/Ryu/RyuJab1.gif",
      "command": "236P"
    },
    {
      "id": "ryu_hadoken_denjin_charge_overdrive",
      "moveName": "Hadoken (Denjin Charge + Overdrive)",
      "category": "special",
      "onBlock": 2,
      "startup": "12",
      "active": "...",
      "recovery": null,
      "punishWindow": null,
      "bestPunish": null,
      "notes": null,
      "imageURL": "https://ultimateframedata.com/sf6/hitboxes/Ryu/RyuJab1.gif",
      "command": "236P"
    },
    {
      "id": "ryu_hashogeki_denjin_charge",
      "moveName": "Hashogeki (Denjin Charge)",
      "category": "special",
      "onBlock": 3,
      "startup": "20",
      "active": "6",
      "recovery": null,
      "punishWindow": null,
      "bestPunish": null,
      "notes": null,
      "imageURL": "https://ultimateframedata.com/sf6/hitboxes/Ryu/RyuJab1.gif",
      "command": "214P"
    },
    {
      "id": "ryu_hashogeki_denjin_charge_overdrive",
      "moveName": "Hashogeki (Denjin Charge + Overdrive)",
      "category": "special",
      "onBlock": 4,
      "startup": "18",
      "active": "6",
      "recovery": null,
      "punishWindow": null,
      "bestPunish": null,
      "notes": null,
      "imageURL": "https://ultimateframedata.com/sf6/hitboxes/Ryu/RyuJab1.gif",
      "command": "214P"
    },
    {
      "id": "ryu_shinku_hadoken_level_1",
      "moveName": "Shinku Hadoken (Level 1)",
      "category": "super",
      "onBlock": -24,
      "startup": "7",
      "active": "**",
      "recovery": null,
      "punishWindow": null,
      "bestPunish": null,
      "notes": null,
      "imageURL": "https://ultimateframedata.com/sf6/hitboxes/Ryu/RyuJab1.gif",
      "command": "236236P"
    },
    {
      "id": "ryu_shin_hashogeki_level_2",
      "moveName": "Shin Hashogeki (Level 2)",
      "category": "super",
      "onBlock": -20,
      "startup": "12",
      "active": "6",
      "recovery": null,
      "punishWindow": null,
      "bestPunish": null,
      "notes": null,
      "imageURL": "https://ultimateframedata.com/sf6/hitboxes/Ryu/RyuJab1.gif",
      "command": "214214P"
    },
    {
      "id": "ryu_shin_shoryuken_level_3",
      "moveName": "Shin Shoryuken (Level 3)",
      "category": "super",
      "onBlock": -52,
      "startup": "5",
      "active": "12",
      "recovery": null,
      "punishWindow": null,
      "bestPunish": null,
      "notes": null,
      "imageURL": "https://ultimateframedata.com/sf6/hitboxes/Ryu/RyuJab1.gif",
      "command": "236236K"
    }
  ],
  "meatySetups": [
    {
      "id": "jackknife_hk_safe_jump",
      "afterMove": "Jackknife Maximum (HK)",
      "kdAdvantage": 42,
      "setup": "Neutral Jump → j.X (Safe Jump)",
      "beats": [
        "SA2 Shin Shoryuken",
        "SA3 Shin Hashogeki",
        "OD Shoryuken",
        "wake throw"
      ],
      "loses": [],
      "trades": [],
      "notes": "Universal answer. Land before reversal, block, punish. SA1 loses to this too (no full invincibility)."
    },
    {
      "id": "jackknife_hk_meaty_mk",
      "afterMove": "Jackknife Maximum (HK)",
      "kdAdvantage": 42,
      "setup": "Walk forward → meaty cr.MK",
      "beats": [
        "wake jab",
        "wake throw",
        "SA1 Shinku Hadoken"
      ],
      "loses": [
        "SA2 Shin Shoryuken (fully invincible)",
        "SA3 Shin Hashogeki (fully invincible)",
        "OD Shoryuken (strike invincible)"
      ],
      "trades": [],
      "notes": "Risky vs reversal-happy Ryu. Use safe jump if they have super meter."
    },
    {
      "id": "forward_throw_loop",
      "afterMove": "MK Rolling Sobat / Forward Throw",
      "kdAdvantage": 34,
      "setup": "Forward Dash → Whiff 5LP → Throw Loop",
      "beats": [
        "wake throw",
        "shimmy bait"
      ],
      "loses": [
        "SA2 Shin Shoryuken",
        "SA3 Shin Hashogeki",
        "OD Shoryuken"
      ],
      "trades": [],
      "notes": "OD Shoryuken is strike invincible but not throw invincible — delayed throw CAN beat it, but timing is strict."
    },
    {
      "id": "back_throw_meaty_lp",
      "afterMove": "Back Throw",
      "kdAdvantage": 22,
      "setup": "Walk-in meaty 5LP",
      "beats": [
        "wake throw"
      ],
      "loses": [
        "SA2 Shin Shoryuken",
        "SA3 Shin Hashogeki",
        "OD Shoryuken"
      ],
      "trades": [],
      "notes": "Minimal oki after back throw. Keep it simple."
    }
  ],
  "wakeupSuperKillers": [
    {
      "id": "safe_jump_universal",
      "title": "Safe Jump (Universal Reversal Killer)",
      "afterMove": "Jackknife Maximum (HK)",
      "kdAdvantage": 42,
      "setup": "Neutral Jump → j.X",
      "beats": [
        "SA2 Shin Shoryuken",
        "SA3 Shin Hashogeki",
        "OD Shoryuken",
        "wake throw"
      ],
      "loses": [],
      "trades": [],
      "punishAfterBlockedSA1": null,
      "punishAfterBlockedSA3": "cr.MP > DR cr.MP xx Jackknife HK (extend w/ OD/super)",
      "notes": "Ryu has two fully invincible supers (SA2 and SA3). Safe jump is the reliable answer to both."
    },
    {
      "id": "meaty_jab_sa1_killer",
      "title": "Meaty 5LP (SA1 Killer)",
      "afterMove": "Any knockdown",
      "kdAdvantage": null,
      "setup": "Well-timed meaty 5LP",
      "beats": [
        "SA1 Shinku Hadoken (projectile inv only)",
        "wake throw",
        "wake jab"
      ],
      "loses": [
        "SA2 Shin Shoryuken",
        "SA3 Shin Hashogeki",
        "OD Shoryuken"
      ],
      "trades": [],
      "punishAfterBlockedSA1": "cr.MP > DR cr.MP xx Jackknife HK",
      "punishAfterBlockedSA3": null,
      "notes": "SA1 has no full strike invincibility — meaty beats it. Risky if they have SA2/SA3 meter."
    }
  ],
  "opponentReversals": [
    {
      "name": "SA1 — Shinku Hadoken",
      "invincibility": "Projectile invincible only",
      "onBlock": -12,
      "warning": "No full strike invincibility — meaty normals beat it cleanly"
    },
    {
      "name": "SA2 — Shin Shoryuken",
      "invincibility": "Fully invincible f1–10",
      "onBlock": -30,
      "warning": "His main reversal super — requires safe jump or deliberate bait"
    },
    {
      "name": "SA3 — Shin Hashogeki",
      "invincibility": "Fully invincible f1–11",
      "onBlock": -35,
      "warning": "Expensive but huge damage on hit — safe jump beats it"
    },
    {
      "name": "OD Shoryuken",
      "invincibility": "Strike invincible f1–8",
      "onBlock": -30,
      "warning": "Strike invincible only — delayed throw can beat it, safe jump is safest"
    }
  ]
}